{
  "type": "Program",
  "body": [
    {
      "type": "VariableDeclaration",
      "declarations": [
        {
          "type": "VariableDeclarator",
          "id": { "type": "Identifier", "name": "test" },
          "init": { "type": "Literal", "value": 1, "raw": "1" }
        }
      ],
      "kind": "let"
    },
    {
      "type": "ExpressionStatement",
      "expression": {
        "type": "UpdateExpression",
        "operator": "++",
        "prefix": false,
        "argument": {
          "type": "Identifier",
          "name": "test"
        }
      }
    }
  ],
  "sourceType": "module"
}
